<?xml version="1.0" encoding="UTF-8"?>
<launch4jConfig>
  <dontWrapJar>false</dontWrapJar>
  <headerType>gui</headerType>
  <jar>../VoidMei.jar</jar>
  <outfile>../VoidMei.exe</outfile>
  <errTitle></errTitle>
  <cmdLine></cmdLine>
  <chdir>.</chdir>
  <priority>high</priority>
  <downloadUrl>http://java.com/download</downloadUrl>
  <supportUrl></supportUrl>
  <stayAlive>false</stayAlive>
  <restartOnCrash>false</restartOnCrash>
  <manifest></manifest>
  <icon>voidmei.ico</icon>
  <singleInstance>
    <mutexName>VoidMei</mutexName>
    <windowTitle></windowTitle>
  </singleInstance>
  <jre>
    <path>%JAVA_HOME%;%PATH%</path>
    <requiresJdk>false</requiresJdk>
    <requires64Bit>false</requires64Bit>
    <minVersion>1.8</minVersion>
    <maxVersion></maxVersion>
    <initialHeapSize>64</initialHeapSize>
    <maxHeapSize>320</maxHeapSize>
  </jre>
  <versionInfo>
    <fileVersion>1.0.0.0</fileVersion>
    <txtFileVersion>1.0</txtFileVersion>
    <fileDescription>1.0</fileDescription>
    <copyright>1.0</copyright>
    <productVersion>1.0.0.0</productVersion>
    <txtProductVersion>1.0</txtProductVersion>
    <productName>VoidMei</productName>
    <companyName>MatrixSukhoi</companyName>
    <internalName>MatrixSukhoi</internalName>
    <originalFilename>VoidMei.exe</originalFilename>
    <trademarks>Matrixsukhoi</trademarks>
    <language>ENGLISH_US</language>
  </versionInfo>
</launch4jConfig>